libtextworker/__init__.py
libtextworker/_importer.py
libtextworker/general.py
libtextworker/get_config.py
libtextworker/interface/__init__.py
libtextworker/interface/_colors.py
libtextworker/interface/manager.py
libtextworker/interface/tk/__init__.py
libtextworker/interface/tk/editor.py
libtextworker/interface/tk/miscs.py
libtextworker/interface/wx/__init__.py
libtextworker/interface/wx/about.py
libtextworker/interface/wx/constants.py
libtextworker/interface/wx/dirctrl.py
libtextworker/interface/wx/editor.py
libtextworker/interface/wx/miscs.py
libtextworker/licenses/AGPL_full.txt
libtextworker/licenses/AGPL_short.txt
libtextworker/licenses/GPL3_full.txt
libtextworker/licenses/GPL3_short.txt
libtextworker/licenses/LGPL_3.txt
libtextworker/licenses/MIT.txt
libtextworker/versioning.py
libtextworker-0.1.3.dist-info/LICENSE
libtextworker-0.1.3.dist-info/METADATA
libtextworker-0.1.3.dist-info/WHEEL
libtextworker-0.1.3.dist-info/RECORD
